mcp_neo4j_memory/__init__.py
mcp_neo4j_memory/neo4j_memory.py
mcp_neo4j_memory/server.py
neo4j_mcp_memory_scccy-0.2.2.dist-info/METADATA
neo4j_mcp_memory_scccy-0.2.2.dist-info/WHEEL
neo4j_mcp_memory_scccy-0.2.2.dist-info/entry_points.txt
neo4j_mcp_memory_scccy-0.2.2.dist-info/RECORD
