Metadata-Version: 2.4
Name: neo4j-mcp-memory-scccy
Version: 0.2.2
Summary: MCP Neo4j Knowledge Graph Memory Server
Requires-Python: >=3.10
Requires-Dist: fastmcp>=2.0.0
Requires-Dist: neo4j>=5.26.0
Requires-Dist: pydantic>=2.10.1
